dfquick/__init__.py
dfquick/dfquick.py
dfquick-0.1.4.dist-info/METADATA
dfquick-0.1.4.dist-info/WHEEL
dfquick-0.1.4.dist-info/top_level.txt
dfquick-0.1.4.dist-info/RECORD
