Metadata-Version: 2.1
Name: dfquick
Version: 0.1.4
Summary: Library to create custom dataframe quickly
Author: Marcel Tino
Author-email: <marceltino92@gmail.com>
Keywords: dataframe,quick
Requires-Dist: pandas
Requires-Dist: datetime
Requires-Dist: numpy
